gxhash-3.4.1.dist-info/METADATA
gxhash-3.4.1.dist-info/WHEEL
gxhash-3.4.1.dist-info/licenses/LICENSE
gxhashpy/__init__.py
gxhashpy/gxhashpy.cp312-win_amd64.pyd
gxhash-3.4.1.dist-info/RECORD
