Metadata-Version: 2.4
Name: gxhash
Version: 3.4.1
Classifier: Programming Language :: Rust
Classifier: Programming Language :: Python :: Implementation :: CPython
Classifier: Programming Language :: Python :: Implementation :: PyPy
License-File: LICENSE
Summary: GxHash non-cryptographic algorithm
Keywords: hash,hasher,hashmap,no-std,crypto
Author: Olivier Giniaux
License: MIT
Requires-Python: >=3.8
Project-URL: Source Code, https://github.com/ogxd/gxhash
